qiskit_noise_analysis/__init__.py
qiskit_noise_analysis/main.py
qiskit_noise_analysis-0.1.5.dist-info/licenses/LICENSE
qiskit_noise_analysis-0.1.5.dist-info/METADATA
qiskit_noise_analysis-0.1.5.dist-info/WHEEL
qiskit_noise_analysis-0.1.5.dist-info/top_level.txt
qiskit_noise_analysis-0.1.5.dist-info/RECORD
