Metadata-Version: 2.4
Name: qiskit_noise_analysis
Version: 0.1.5
Summary: A qiskit based library to estimate resources and analyse noise in the quantum circuits.
Home-page: https://pypi.org/project/qiskit-noise-analysis/
Author: Mohit Joshi
Author-email: joshimohit@bhu.ac.in
Project-URL: Bug Tracker, https://github.com/joshicoding/qiskit_noise_analysis/issues
Classifier: Development Status :: 2 - Pre-Alpha
Classifier: Intended Audience :: Science/Research
Classifier: Programming Language :: Python :: 3.13
Classifier: License :: OSI Approved :: MIT License
Classifier: Operating System :: OS Independent
Requires-Python: >=3
License-File: LICENSE
Requires-Dist: qiskit>=1
Requires-Dist: pandas>=2
Requires-Dist: matplotlib>=3
Dynamic: author
Dynamic: author-email
Dynamic: classifier
Dynamic: description
Dynamic: description-content-type
Dynamic: home-page
Dynamic: license-file
Dynamic: project-url
Dynamic: requires-dist
Dynamic: requires-python
Dynamic: summary
